search1688api/__init__.py
search1688api/async_session.py
search1688api/models.py
search1688api/sync_session.py
search1688api/utils.py
search1688api-1.0.1.dist-info/METADATA
search1688api-1.0.1.dist-info/WHEEL
search1688api-1.0.1.dist-info/top_level.txt
search1688api-1.0.1.dist-info/RECORD
