Metadata-Version: 2.4
Name: search1688api
Version: 1.0.1
Summary: Python library for searching products on 1688.com by image
Author: netkaruma
Author-email: suzumekaruma@gmail.com
Requires-Python: >=3.7
Requires-Dist: requests>=2.25.0
Requires-Dist: aiohttp>=3.8.0
Requires-Dist: yarl>=1.6.0
Dynamic: author
Dynamic: author-email
Dynamic: requires-dist
Dynamic: requires-python
Dynamic: summary
